nutrimetrics/.DS_Store
nutrimetrics/__about__.py
nutrimetrics/__init__.py
nutrimetrics/cli.py
nutrimetrics/config.py
nutrimetrics/food_data_central.py
nutrimetrics/meals.py
nutrimetrics/nutrients.py
nutrimetrics/units.py
nutrimetrics/workbook.py
nutrimetrics/resources/.DS_Store
nutrimetrics/resources/config.json
nutrimetrics/resources/dri/ear-female.json
nutrimetrics/resources/dri/ear-male.json
nutrimetrics/resources/dri/rda-female.json
nutrimetrics/resources/dri/rda-male.json
nutrimetrics/resources/foods/.DS_Store
nutrimetrics/resources/foods/almond_170567.json
nutrimetrics/resources/foods/almond_butter_168588.json
nutrimetrics/resources/foods/almond_milk_2257045.json
nutrimetrics/resources/foods/apple_171689.json
nutrimetrics/resources/foods/apple_cider_vinegar_173469.json
nutrimetrics/resources/foods/apricot_171697.json
nutrimetrics/resources/foods/asparagus_168389.json
nutrimetrics/resources/foods/avocado_171705.json
nutrimetrics/resources/foods/balsamic_vinegar_172241.json
nutrimetrics/resources/foods/banana_173944.json
nutrimetrics/resources/foods/basil_172232.json
nutrimetrics/resources/foods/beef_ground_80-20_174036.json
nutrimetrics/resources/foods/beef_ground_90-10_174030.json
nutrimetrics/resources/foods/beetroot_169145.json
nutrimetrics/resources/foods/bell_pepper_green_2258588.json
nutrimetrics/resources/foods/bell_pepper_orange_2258591.json
nutrimetrics/resources/foods/bell_pepper_red_2258590.json
nutrimetrics/resources/foods/bell_pepper_yellow_2258589.json
nutrimetrics/resources/foods/black_bean_173734.json
nutrimetrics/resources/foods/blackberry_173946.json
nutrimetrics/resources/foods/blueberry_171711.json
nutrimetrics/resources/foods/brazil_nut_170569.json
nutrimetrics/resources/foods/brewed_coffee_171890.json
nutrimetrics/resources/foods/broccoli_170379.json
nutrimetrics/resources/foods/brussels_sprout_170383.json
nutrimetrics/resources/foods/butter_173430.json
nutrimetrics/resources/foods/cabbage_169975.json
nutrimetrics-1.0.0.dist-info/METADATA
nutrimetrics-1.0.0.dist-info/WHEEL
nutrimetrics-1.0.0.dist-info/entry_points.txt
nutrimetrics-1.0.0.dist-info/license_files/LICENSE
nutrimetrics-1.0.0.dist-info/RECORD
