Metadata-Version: 2.1
Name: nutrimetrics
Version: 1.0.0
Summary: Analyzes nutrients found in foods and user-defined meal plans.
Project-URL: Issues, https://github.com/tomcv/nutrimetrics/issues
Project-URL: Source, https://github.com/tomcv/nutrimetrics
Author-email: Thomas Civeit <thomas@civeit.com>
License: MIT License
Keywords: analysis,calculator,calorie,counter,diet,food,meal,nutrient,nutrition,tracker
Classifier: License :: OSI Approved :: MIT License
Classifier: Operating System :: OS Independent
Classifier: Programming Language :: Python :: 3.10
Classifier: Programming Language :: Python :: 3.11
Classifier: Programming Language :: Python :: 3.9
Requires-Python: >=3.9
Requires-Dist: jsmin
Requires-Dist: requests
Requires-Dist: xlsxwriter
